import_it/__init__.py
import_it/__main__.py
import_it/utils.py
import_it-0.3.0.dist-info/entry_points.txt
import_it-0.3.0.dist-info/WHEEL
import_it-0.3.0.dist-info/METADATA
import_it-0.3.0.dist-info/RECORD
